pattern_library/__init__.py
pattern_library/apps.py
pattern_library/cm_utils.py
pattern_library/context_modifiers.py
pattern_library/exceptions.py
pattern_library/loader_tags.py
pattern_library/management/__init__.py
pattern_library/management/commands/__init__.py
pattern_library/management/commands/render_patterns.py
pattern_library/monkey_utils.py
pattern_library/py.typed
pattern_library/static/pattern_library/dist/bundle.js
pattern_library/templates/pattern_library/base.html
pattern_library/templates/pattern_library/index.html
pattern_library/templates/pattern_library/pattern_group.html
pattern_library/urls.py
pattern_library/utils.py
pattern_library/views.py
django_pattern_library-1.5.0.dist-info/LICENSE
django_pattern_library-1.5.0.dist-info/METADATA
django_pattern_library-1.5.0.dist-info/WHEEL
django_pattern_library-1.5.0.dist-info/RECORD
